shadow_auth/__init__.py
shadow_auth/_internal/__init__.py
shadow_auth/_internal/classes.py
shadow_auth/_internal/enums.py
shadow_auth/_internal/exceptions.py
shadow_auth/_internal/functions.py
shadow_auth/_internal/validations.py
shadow_auth-0.1.dist-info/LICENSE
shadow_auth-0.1.dist-info/METADATA
shadow_auth-0.1.dist-info/WHEEL
shadow_auth-0.1.dist-info/top_level.txt
shadow_auth-0.1.dist-info/RECORD
