Metadata-Version: 2.1
Name: shadow-auth
Version: 0.1
Summary: Python module to validate the credentials of a Linux user using the /etc/shadow file
Home-page: https://github.com/ospinakamilo/linux-shadow-auth/
Author: Camilo A. Ospina A.
Author-email: camilo.ospinaa@gmail.com
License: UNKNOWN
Keywords: shadow_auth linux authentication credentials shadow passwd pam
Platform: UNKNOWN
Classifier: Intended Audience :: Developers
Classifier: Programming Language :: Python :: 3
Classifier: License :: OSI Approved :: Apache Software License
Classifier: Operating System :: POSIX :: Linux
Requires-Python: >3, !=3.0.*, !=3.1.*, !=3.2.*, !=3.3.*, !=3.4.*,  <4
